{
  "bookId": "willkommen-vaughan-31",
  "bookTitle": "Buch 31",
  "sektionId": "sektion-3",
  "sektionTitle": "Sektion 3: lieber (imperativo) + am liebsten (superlativo: me encanta)",
  "order": 3,
  "cards": [
    { "id": "s3-t001", "front": "Mejor que te vayas a casa.", "back": "Geh lieber nach Hause." },
    { "id": "s3-t002", "front": "Mejor que avises.", "back": "Sag lieber Bescheid." },
    { "id": "s3-t003", "front": "Mejor que preguntes de nuevo.", "back": "Frag lieber noch mal." },
    { "id": "s3-t004", "front": "Mejor nos vamos...", "back": "Lass uns lieber gehen..." },
    { "id": "s3-t005", "front": "Mejor que avises a tu madre antes de que se preocupe.", "back": "Sag lieber deiner Mutter Bescheid, bevor sie sich Sorgen macht." },
    { "id": "s3-t006", "front": "Mejor que te vayas a casa antes de que tus padres se preocupen.", "back": "Geh lieber nach Hause, bevor deine Eltern sich Sorgen machen." },
    { "id": "s3-t007", "front": "Mejor que preguntes de nuevo antes de que hagas algo mal.", "back": "Frag lieber noch mal, bevor du etwas falsch machst." },
    { "id": "s3-t008", "front": "Mejor que no hagas eso.", "back": "Mach das lieber nicht." },
    { "id": "s3-t009", "front": "Mejor que no entres ahí.", "back": "Geh lieber nicht dort rein." },
    { "id": "s3-t010", "front": "Mejor que no preguntes.", "back": "Frag lieber nicht." },
    { "id": "s3-t011", "front": "¿Damos una vuelta?", "back": "Wollen wir eine Runde drehen?" },
    { "id": "s3-t012", "front": "Mejor vamos a ver una película.", "back": "Lass uns lieber einen Film gucken." },
    { "id": "s3-t013", "front": "¿Pedimos una pizza?", "back": "Wollen wir Pizza bestellen?" },
    { "id": "s3-t014", "front": "Mejor pedimos comida china.", "back": "Lass uns lieber chinesisches Essen bestellen." },
    { "id": "s3-t015", "front": "¿Nos vamos?", "back": "Wollen wir gehen?" },
    { "id": "s3-t016", "front": "Mejor nos quedamos un rato más aquí.", "back": "Lass uns lieber noch eine Weile hier bleiben." },
    { "id": "s3-t017", "front": "Mejor nos vamos antes de que nos vea alguien.", "back": "Lass uns lieber gehen, bevor jemand uns sieht." },
    { "id": "s3-t018", "front": "Mejor avisamos antes de que alguien se preocupe.", "back": "Lass uns lieber Bescheid sagen, bevor jemand sich Sorgen macht." },
    { "id": "s3-t019", "front": "Mejor preguntamos otra vez antes de que hagamos algo mal.", "back": "Lass uns lieber noch mal fragen, bevor wir etwas falsch machen." },

    { "id": "s3-t020", "front": "Debes fumar menos.", "back": "Du sollst weniger rauchen." },
    { "id": "s3-t021", "front": "Deberías fumar menos.", "back": "Du solltest weniger rauchen." },
    { "id": "s3-t022", "front": "Sería mejor que fumaras menos.", "back": "Du solltest lieber weniger rauchen." },
    { "id": "s3-t023", "front": "Sería mejor que te dieras prisa.", "back": "Du solltest dich lieber beeilen." },
    { "id": "s3-t024", "front": "Sería mejor que te disculparas.", "back": "Du solltest dich lieber entschuldigen." },
    { "id": "s3-t025", "front": "Sería mejor que esperase fuera.", "back": "Sie sollten lieber draußen warten." },
    { "id": "s3-t026", "front": "Sería mejor que hablase más bajo.", "back": "Sie sollten lieber leiser reden." },
    { "id": "s3-t027", "front": "Sería mejor que se disculpase.", "back": "Sie sollten sich lieber entschuldigen." },
    { "id": "s3-t028", "front": "Sería mejor que esperásemos un poco más.", "back": "Wir sollten lieber noch warten." },
    { "id": "s3-t029", "front": "Sería mejor que nos marcháramos pronto.", "back": "Wir sollten lieber bald losfahren." },
    { "id": "s3-t030", "front": "Sería mejor que hiciéramos menos ruido.", "back": "Wir sollten lieber leiser sein." },
    { "id": "s3-t031", "front": "Sería mejor que avisaras antes de que él se preocupe.", "back": "Du solltest lieber Bescheid sagen, bevor er sich Sorgen macht." },
    { "id": "s3-t032", "front": "Sería mejor que preguntara usted de nuevo antes de hacer algo mal.", "back": "Sie sollten lieber noch mal fragen, bevor Sie etwas falsch machen." },
    { "id": "s3-t033", "front": "Sería mejor que hiciéramos menos ruido antes de que los vecinos llamen a la policía.", "back": "Wir sollten lieber leiser sein, bevor die Nachbarn die Polizei rufen." },
    { "id": "s3-t034", "front": "Sería mejor que te abrigaras para que no te pongas malo.", "back": "Du solltest dich lieber warm anziehen, damit du nicht krank wirst." },
    { "id": "s3-t035", "front": "Sería mejor que se diera usted prisa para no llegar tarde.", "back": "Sie sollten sich lieber beeilen, damit Sie nicht zu spät kommen." },
    { "id": "s3-t036", "front": "Sería mejor que fuéramos más despacio para que no tengamos un accidente.", "back": "Wir sollten lieber langsamer fahren, damit wir keinen Unfall haben." },

    { "id": "s3-t037", "front": "Mejor me lo apunto, o si no se me olvida.", "back": "Ich schreibe das lieber auf, sonst vergesse ich das noch." },
    { "id": "s3-t038", "front": "Mejor aviso, o si no mi madre se preocupará.", "back": "Ich sage lieber Bescheid, sonst macht meine Mutter sich noch Sorgen." },
    { "id": "s3-t039", "front": "Mejor bajo la música, o si no vendrá la policía.", "back": "Ich mache lieber die Musik leiser, sonst kommt die Polizei noch." },
    { "id": "s3-t040", "front": "Mejor que te lo apuntes, o si no se te olvidará.", "back": "Schreib' dir das lieber auf, sonst vergisst du das noch." },
    { "id": "s3-t041", "front": "Mejor que se lo apunte, o si no se le olvidará.", "back": "Schreiben Sie sich das lieber auf, sonst vergessen Sie das noch." },
    { "id": "s3-t042", "front": "Mejor que salgas ya, o si no vas a llegar tarde.", "back": "Fahr lieber schon mal los, sonst kommst du noch zu spät." },
    { "id": "s3-t043", "front": "Mejor no haga usted eso, o si no podría tener problemas.", "back": "Machen Sie das lieber nicht, sonst könnten Sie Probleme bekommen." },
    { "id": "s3-t044", "front": "Mejor no aparque usted aquí, o si no le pondrán una multa.", "back": "Parken Sie lieber nicht hier, sonst bekommen Sie einen Strafzettel." },
    { "id": "s3-t045", "front": "Mejor no aparques aquí, o si no te pondrán una multa.", "back": "Park lieber nicht hier, sonst bekommst du einen Strafzettel." },
    { "id": "s3-t046", "front": "Sería mejor que dieras señales, o si no tu madre se va a preocupar.", "back": "Du solltest dich lieber melden, sonst macht sich deine Mutter Sorgen." },
    { "id": "s3-t047", "front": "Sería mejor que no hiciera usted eso, o si no podría tener problemas.", "back": "Sie sollten das lieber nicht tun, sonst könnten Sie ein Problem bekommen." },
    { "id": "s3-t048", "front": "Sería mejor que nos diéramos prisa, o si no vamos a llegar tarde.", "back": "Wir sollten uns lieber beeilen, sonst kommen wir noch zu spät." },
    { "id": "s3-t049", "front": "Mejor que vayamos en coche, o si no llegaremos tarde.", "back": "Lass uns lieber mit dem Auto fahren, sonst kommen wir zu spät." },
    { "id": "s3-t050", "front": "Mejor que nos vayamos ya, o si no nos verá alguien.", "back": "Lass uns lieber gehen, sonst sieht jemand uns noch." },
    { "id": "s3-t051", "front": "Mejor que nos lo apuntemos, o si no se nos va a olvidar.", "back": "Lass uns das lieber aufschreiben, sonst vergessen wir das noch." },

    { "id": "s3-t052", "front": "Hola, un helado de tres bolas para llevar, por favor.", "back": "Hallo, ich hätte gerne ein Eis mit drei Kugeln zum Mitnehmen." },
    { "id": "s3-t053", "front": "En cucurucho, por favor.", "back": "Im Hörnchen, bitte." },
    { "id": "s3-t054", "front": "Una bola de fresa y dos bolas de vainilla.", "back": "Ich hätte gerne eine Kugel Erdbeer und zwei Kugeln Vanille." },
    { "id": "s3-t055", "front": "Mejor sin nata.", "back": "Lieber ohne Sahne." },
    { "id": "s3-t056", "front": "¿En cucurucho o en tarrina?", "back": "Im Hörnchen oder im Becher?" },
    { "id": "s3-t057", "front": "¿Qué sabores quiere?", "back": "Welche Sorten hätten Sie gerne?" },
    { "id": "s3-t058", "front": "¿Con o sin nata?", "back": "Mit oder ohne Sahne?" },
    { "id": "s3-t059", "front": "Aquí tiene. Son 3 euros, por favor.", "back": "Hier bitte, das macht 3 €." },

    { "id": "s3-t060", "front": "Cuando más me gusta leer es antes de irme a dormir.", "back": "Ich lese am liebsten vorm Schlafengehen." },
    { "id": "s3-t061", "front": "Cuando más me gusta ir al mercado semanal es los sábados por la mañana.", "back": "Ich gehe am liebsten am Samstag Morgen auf den Wochenmarkt." },
    { "id": "s3-t062", "front": "Cuando más me gusta hacer footing es por las mañanas.", "back": "Ich gehe am liebsten morgens joggen." },
    { "id": "s3-t063", "front": "Cuando estoy de vacaciones, lo que más me gusta leer son novelas policíacas.", "back": "Wenn ich im Urlaub bin, lese ich am liebsten Krimis." },
    { "id": "s3-t064", "front": "Cuando estoy en el trabajo, lo que más me gusta escuchar es música clásica.", "back": "Wenn ich bei der Arbeit bin, höre ich am liebsten klassische Musik." },
    { "id": "s3-t065", "front": "Cuando libro, me encanta levantarme tarde.", "back": "Wenn ich frei habe, stehe ich am liebsten spät auf." },
    { "id": "s3-t066", "front": "¿Te gusta ir a la piscina?", "back": "Gehst du gerne ins Schwimmbad?" },
    { "id": "s3-t067", "front": "Sí, pero donde más me gusta bañarme es en el mar.", "back": "Ja, aber ich bade am liebsten im Meer." },
    { "id": "s3-t068", "front": "¿Te gusta ir a la ópera?", "back": "Gehst du gerne in die Oper?" },
    { "id": "s3-t069", "front": "Sí, pero donde más me gusta ir es al teatro.", "back": "Ja, aber ich gehe am liebsten ins Theater." },
    { "id": "s3-t070", "front": "¿Te gusta ir a esquiar?", "back": "Gehst du gerne skifahren?" },
    { "id": "s3-t071", "front": "Sí, pero lo que más me gusta hacer es navegar a vela.", "back": "Ja, aber ich gehe am liebsten segeln." },
    { "id": "s3-t072", "front": "Lo que más me gusta para desayunar es un café.", "back": "Ich habe am liebsten Kaffee zum Frühstück." },
    { "id": "s3-t073", "front": "El que más me gusta es el pan integral.", "back": "Ich habe am liebsten Vollkornbrot." },
    { "id": "s3-t074", "front": "Lo que más me gusta para desayunar son los panecillos frescos.", "back": "Ich habe am liebsten frische Brötchen zum Frühstück." },
    { "id": "s3-t075", "front": "El pan integral es el que más me gusta.", "back": "Vollkornbrot ist mir am liebsten." },
    { "id": "s3-t076", "front": "Los panecillos frescos son los que más me gustan.", "back": "Frische Brötchen sind mir am liebsten." },
    { "id": "s3-t077", "front": "El café es lo que más me gusta para desayunar.", "back": "Kaffee zum Frühstück ist mir am liebsten." },

    { "id": "s3-t078", "front": "Me encantaría estar ya de vacaciones.", "back": "Ich wäre am liebsten schon im Urlaub." },
    { "id": "s3-t079", "front": "Ahora mismo me encantaría estar bien lejos.", "back": "Ich wäre jetzt am liebsten ganz weit weg." },
    { "id": "s3-t080", "front": "Me encantaría estar contigo.", "back": "Ich wäre am liebsten bei dir." },
    { "id": "s3-t081", "front": "Me encantaría tener un piso antiguo con ático.", "back": "Ich hätte am liebsten eine Altbauwohnung mit Dachterrasse." },
    { "id": "s3-t082", "front": "Me encantaría tener mi propio caballo.", "back": "Ich hätte am liebsten mein eigenes Pferd." },
    { "id": "s3-t083", "front": "Me encantaría tener una casa en la playa.", "back": "Ich hätte am liebsten ein Haus am Meer." },
    { "id": "s3-t084", "front": "Si pudiera elegir, me encantaría tener todo el verano libre.", "back": "Wenn ich die Wahl hätte, hätte ich am liebsten den ganzen Sommer frei." },
    { "id": "s3-t085", "front": "Si pudiera elegir, me encantaría tener un piso antiguo con ático.", "back": "Wenn ich die Wahl hätte, hätte ich am liebsten eine Altbauwohnung mit Dachterrasse." },
    { "id": "s3-t086", "front": "Si pudiera elegir, me encantaría ser cantante de ópera.", "back": "Wenn ich die Wahl hätte, wäre ich am liebsten Opernsängerin." },
    { "id": "s3-t087", "front": "Me encantaría tener tranquilidad.", "back": "Es wäre mir am liebsten, wenn ich meine Ruhe hätte." },
    { "id": "s3-t088", "front": "Me encantaría que lo hiciera otra persona.", "back": "Es wäre mir am liebsten, wenn das jemand anders machen würde." },
    { "id": "s3-t089", "front": "Me encantaría que eso no volviera a pasar.", "back": "Es wäre mir am liebsten, wenn das nicht noch mal passieren würde." },
    { "id": "s3-t090", "front": "Me encantaría que me dejarais en paz.", "back": "Ich hätte es am liebsten, wenn ihr mich in Ruhe lassen würdet." },
    { "id": "s3-t091", "front": "Me encantaría poder irme mañana ya de vacaciones.", "back": "Ich hätte es am liebsten, wenn ich morgen schon in den Urlaub fahren könnte." },
    { "id": "s3-t092", "front": "Me encantaría que eso no volviera a pasar (a mí).", "back": "Ich hätte es am liebsten, wenn das nicht noch mal passieren würde." },

    { "id": "s3-t093", "front": "Me encantaría salir corriendo.", "back": "Ich würde am liebsten wegrennen." },
    { "id": "s3-t094", "front": "Me encantaría tomarme un año libre.", "back": "Ich würde mir am liebsten ein Jahr freinehmen." },
    { "id": "s3-t095", "front": "Ahora mismo me encantaría darme una vuelta.", "back": "Ich würde jetzt am liebsten eine Runde drehen." },
    { "id": "s3-t096", "front": "Me encantaría preguntarle (a él) yo mismo.", "back": "Ich würde ihn am liebsten selbst fragen." },
    { "id": "s3-t097", "front": "Me encantaría hacerlo yo mismo.", "back": "Ich würde es am liebsten selbst machen." },
    { "id": "s3-t098", "front": "Me encantaría decírselo (a ella) yo mismo.", "back": "Ich würde es ihr am liebsten selbst sagen." },
    { "id": "s3-t099", "front": "Me encantaría decirle cuatro cosas a mi jefe.", "back": "Ich würde meinem Chef am liebsten die Meinung sagen." },
    { "id": "s3-t100", "front": "Me encantaría decirle cuatro cosas a él.", "back": "Ich würde ihm am liebsten die Meinung sagen." },
    { "id": "s3-t101", "front": "Me encantaría cantarle las cuarenta a ella.", "back": "Ich würde ihr am liebsten mal richtig die Meinung sagen." },
    { "id": "s3-t102", "front": "Si pudiera, me encantaría tomarme un año libre.", "back": "Wenn ich könnte, würde ich mir am liebsten ein Jahr freinehmen." },
    { "id": "s3-t103", "front": "Si pudiera, me encantaría decirle cuatro cosas.", "back": "Wenn ich könnte, würde ich ihm am liebsten die Meinung sagen." },
    { "id": "s3-t104", "front": "Si pudiera, me encantaría verlo yo mismo.", "back": "Wenn ich könnte, würde ich es am liebsten selbst sehen." },
    { "id": "s3-t105", "front": "¡Me encantaría mandarla a freír espárragos!", "back": "Ich würde sie am liebsten auf den Mond schicken!" },
    { "id": "s3-t106", "front": "¡A veces me encantaría mandarle a freír espárragos!", "back": "Ich würde ihn manchmal am liebsten auf den Mond schicken!" },
    { "id": "s3-t107", "front": "¡A veces me encantaría mandar a mi hija a freír espárragos!", "back": "Ich würde meine Tochter manchmal am liebsten auf den Mond schicken!" },

    { "id": "s3-t108", "front": "¡De nada! / Nada que agradecer (frase clave)", "back": "Nichts zu danken!" },
    { "id": "s3-t109", "front": "No se admiten pasajeros (letrero, lit. 'viaje vacío')", "back": "Leerfahrt" },
    { "id": "s3-t110", "front": "No subir, por favor (letrero)", "back": "Bitte nicht einsteigen" },

    { "id": "s3-t111", "front": "la multa", "back": "der Strafzettel" },
    { "id": "s3-t112", "front": "el mercado semanal", "back": "der Wochenmarkt" },
    { "id": "s3-t113", "front": "el accidente", "back": "der Unfall" },
    { "id": "s3-t114", "front": "la película", "back": "der Film" },
    { "id": "s3-t115", "front": "el piso antiguo (bonito)", "back": "die Altbauwohnung" },
    { "id": "s3-t116", "front": "la elección", "back": "die Wahl" },
    { "id": "s3-t117", "front": "la cantante de ópera", "back": "die Opernsängerin" },
    { "id": "s3-t118", "front": "el rato / la temporada", "back": "die Weile" },
    { "id": "s3-t119", "front": "el pan integral", "back": "das Vollkornbrot" },
    { "id": "s3-t120", "front": "la piscina", "back": "das Schwimmbad" },
    { "id": "s3-t121", "front": "el mar", "back": "das Meer" },
    { "id": "s3-t122", "front": "o si no / en caso contrario", "back": "sonst" },
    { "id": "s3-t123", "front": "antes de dormir", "back": "vorm Schlafengehen" },
    { "id": "s3-t124", "front": "bien lejos", "back": "ganz weit weg" },
    { "id": "s3-t125", "front": "antes de que", "back": "bevor" },
    { "id": "s3-t126", "front": "por sí mismo / yo mismo", "back": "selbst" },
    { "id": "s3-t127", "front": "las novelas/películas policíacas", "back": "die Krimis" },
    { "id": "s3-t128", "front": "los panecillos", "back": "die Brötchen" },
    { "id": "s3-t129", "front": "los padres", "back": "die Eltern" },
    { "id": "s3-t130", "front": "darse prisa", "back": "sich beeilen" },
    { "id": "s3-t131", "front": "apuntar", "back": "aufschreiben" },
    { "id": "s3-t132", "front": "disculparse", "back": "sich entschuldigen" },
    { "id": "s3-t133", "front": "esquiar", "back": "skifahren" },
    { "id": "s3-t134", "front": "navegar a vela", "back": "segeln" },
    { "id": "s3-t135", "front": "tomarse (tiempo) libre", "back": "sich freinehmen" },
    { "id": "s3-t136", "front": "preocuparse", "back": "sich Sorgen machen" },
    { "id": "s3-t137", "front": "entrar", "back": "reingehen" },
    { "id": "s3-t138", "front": "dar(se) una vuelta", "back": "eine Runde drehen" },
    { "id": "s3-t139", "front": "ver / mirar (coloquial)", "back": "gucken" },
    { "id": "s3-t140", "front": "pedir / encargar", "back": "bestellen" },
    { "id": "s3-t141", "front": "salir / marcharse (en coche)", "back": "losfahren" },
    { "id": "s3-t142", "front": "tener problemas", "back": "Probleme bekommen" },
    { "id": "s3-t143", "front": "comunicarse / dar señales de vida", "back": "sich melden" },

    { "id": "s3-g001", "front": "¿Qué es «lieber» y dónde se coloca?", "back": "Es el comparativo de «gerne» ('con gusto'); significa 'mejor (que)' / 'preferiblemente'. Se coloca detrás del verbo. Escala completa: gerne (básico) → lieber (comparativo, ++) → am liebsten (superlativo, +++). En esta Sektion se deja de lado el sentido de 'preferir'." },
    { "id": "s3-g002", "front": "¿Cómo se usa «lieber» en imperativo afirmativo?", "back": "Verbo en imperativo (sin la -e final: Geh, Sag, Frag) + «lieber» detrás → «Geh lieber nach Hause» ('Mejor que te vayas a casa'). Con «Lass uns...» ('Vamos a...'), «lieber» va detrás del pronombre «uns»: «Lass uns lieber gehen»." },
    { "id": "s3-g003", "front": "¿Cómo se forma el imperativo negativo con «lieber»?", "back": "Verbo mandón + «lieber nicht» → «Mach das lieber nicht» ('Mejor que no hagas eso'). El complemento directo va detrás de «lieber», pero el pronombre «das» ('eso/lo') tiene prioridad y va justo detrás del verbo." },
    { "id": "s3-g004", "front": "¿Qué es «bevor» y qué le hace al verbo?", "back": "«bevor» = 'antes de que'. Es conjunción subordinante, así que manda el verbo conjugado al FINAL de la subordinada: «Geh lieber nach Hause, bevor deine Eltern sich Sorgen machen»." },
    { "id": "s3-g005", "front": "¿Cómo se suaviza un consejo con «sollen» en K-II?", "back": "Se usa el Konjunktiv II: du solltest / Sie sollten / wir sollten = 'deberías / debería / deberíamos'. «Du sollst weniger rauchen» (Debes) → «Du solltest weniger rauchen» (Deberías). Se puede sustituir «lieber» por «besser» ('mejor'). El verbo principal va en infinitivo al final." },
    { "id": "s3-g006", "front": "En «Du solltest dich lieber beeilen», ¿dónde va el pronombre reflexivo?", "back": "El pronombre reflexivo (dich/sich) va justo después de «sollen/solltest» y ANTES del adverbio «lieber»: «Du solltest dich lieber beeilen», «Sie sollten sich lieber entschuldigen»." },
    { "id": "s3-g007", "front": "¿Qué es «damit» y qué le hace al verbo?", "back": "«damit» = 'para que'. Conjunción subordinante → el verbo conjugado va al FINAL: «Du solltest dich lieber warm anziehen, damit du nicht krank wirst» ('...para que no te pongas malo')." },
    { "id": "s3-g008", "front": "¿Qué es «sonst» y qué provoca al principio de una frase?", "back": "«sonst» = 'o si no' / 'de lo contrario'. Cuando encabeza la frase secundaria exige la inversión sujeto-verbo: «..., sonst macht sie sich Sorgen». Suele acompañarse de la muletilla «noch» ('seguro que...si no'): «..., sonst vergesse ich das noch»." },
    { "id": "s3-g009", "front": "¿Cómo se dice 'hacer algo mal' y 'tener problemas' en alemán?", "back": "'Hacer algo mal' = «etwas falsch machen» (NO «etwas schlecht machen»). 'Tener problemas' = «Probleme bekommen». der Strafzettel = 'multa'. Ojo: para 'avisar' a la policía se usa «rufen» (no «anrufen»)." },
    { "id": "s3-g010", "front": "¿Qué es «am liebsten» y dónde se coloca?", "back": "Es el superlativo de «gerne»: 'lo que más me gusta' / 'me encanta'. Se coloca detrás del verbo conjugado; cuando hay inversión, va detrás del sujeto: «Wenn ich bei der Arbeit bin, höre ich am liebsten klassische Musik»." },
    { "id": "s3-g011", "front": "¿En qué se diferencian «Ich habe am liebsten...» e «Ich hätte am liebsten...»?", "back": "«Ich habe am liebsten...» (indicativo) = preferencias/gustos EN GENERAL ('lo que más me gusta es...'). «Ich hätte am liebsten...» (K-II) = un deseo o preferencia CONCRETA e irreal ('me encantaría tener...')." },
    { "id": "s3-g012", "front": "¿Qué significa «X ist mir am liebsten»?", "back": "'X es lo que más me gusta'. Se usa un pronombre personal en dativo para expresar a quién le gusta: mir/ihm/uns/ihnen. «Vollkornbrot ist mir am liebsten», «Frische Brötchen sind mir am liebsten»." },
    { "id": "s3-g013", "front": "¿Qué expresan «Ich wäre am liebsten...» e «Ich hätte am liebsten...»?", "back": "«Ich wäre am liebsten...» = 'Me encantaría estar/ser...' (sein en K-II = wäre). «Ich hätte am liebsten...» = 'Me encantaría tener...' (haben en K-II = hätte). Aportan el matiz irreal del deseo." },
    { "id": "s3-g014", "front": "¿Cómo se dice 'Me encantaría que...'?", "back": "«Es wäre mir am liebsten, wenn...» o «Ich hätte es am liebsten, wenn...». En la subordinada con «wenn» el verbo en K-II va al FINAL: «Es wäre mir am liebsten, wenn das jemand anders machen würde»." },
    { "id": "s3-g015", "front": "¿Qué es «die Wahl haben» y cómo se usa?", "back": "«die Wahl haben» = 'poder elegir / tener la elección'. «Wenn ich die Wahl hätte, hätte ich am liebsten...» = 'Si pudiera elegir, me encantaría...' (con inversión tras la subordinada). die Wahl = 'elección'; wählen = 'elegir/votar'." },
    { "id": "s3-g016", "front": "¿Cuándo se usa «Ich würde am liebsten...» y dónde van los pronombres?", "back": "Para verbos que NO tienen forma propia de K-II se usa «würde» + infinitivo al final: «Ich würde am liebsten wegrennen» ('Me encantaría salir corriendo'). Los pronombres (es, ihr, mir) van ENTRE «ich würde» y «am liebsten»: «Ich würde es ihr am liebsten sagen»." },
    { "id": "s3-g017", "front": "¿Qué significa «jemandem die Meinung sagen»?", "back": "'Decirle cuatro cosas a alguien'. La persona va en dativo: «meinem Chef», «ihm», «ihr». Añadiendo «mal richtig» ('cantarle las cuarenta'): «Ich würde ihr am liebsten mal richtig die Meinung sagen»." },
    { "id": "s3-g018", "front": "¿Qué significa la expresión «jemanden auf den Mond schicken»?", "back": "Literalmente 'mandar a alguien a la luna' = 'mandar a freír espárragos'. der Mond = 'la luna', die Sonne = 'el sol'. Se dice «auf den Mond» (acusativo) porque «auf» rige acusativo cuando hay movimiento." },
    { "id": "s3-g019", "front": "¿Qué significan «selbst/selber» y «(sich) freinehmen / frei haben»?", "back": "«selbst» (o «selber») = 'por sí mismo / yo mismo', invariable. «sich freinehmen» = 'tomarse (tiempo) libre' (frei = 'libre' + nehmen = 'tomar'); «frei haben» = 'librar'." },
    { "id": "s3-g020", "front": "Vocabulario de la heladería (Deutsch im Kontext: In der Eisdiele)", "back": "die Eisdiele / das Eiscafé = heladería; das Eis = helado/hielo; das Hörnchen / die Waffel = cucurucho / barquillo; der Becher = tarrina; die Kugel = bola; die Sorte = sabor/tipo; die Sahne = nata; zum Mitnehmen = para llevar (zu + mitnehmen)." },
    { "id": "s3-g021", "front": "Frase clave: «Nichts zu danken!»", "back": "Significa '¡De nada!' (lit. 'nada que agradecer'; danken = 'dar las gracias'). Es una cuarta forma junto a «Kein Problem», «Keine Ursache» y «Gern geschehen»." },
    { "id": "s3-g022", "front": "Esta vez visitamos: Emden", "back": "La ciudad más grande de Ostfriesland (Frisia Oriental), en Baja Sajonia (Niedersachsen), ~50.000 habitantes. Conocida como la 'Ciudad del Agua' («Wasserstadt»); ~7% de su superficie es agua (150 km de canales). Se habla el dialecto «Ostfriesisches Platt». Famoso: Otto Walkes, uno de los cómicos más famosos de Alemania." },
    { "id": "s3-g023", "front": "Alemanes famosos: Pina Bausch (1940-2009)", "back": "Bailarina y coreógrafa (Tänzerin und Choreographin), pionera de la danza contemporánea; dirigió el Tanztheater Wuppertal. Su frase: «Tanz weckt Erinnerungen, Gefühle, Hoffnungen. Das verbindet uns alle» ('La danza despierta recuerdos, sentimientos, esperanzas. Esto nos conecta a todos'). Gefühle = 'sentimientos'." }
  ]
}
