{
  "bookId": "willkommen-vaughan-11",
  "bookTitle": "Buch 11",
  "sektionId": "sektion-1",
  "sektionTitle": "Sektion 1: zu viel / zu viele / genug",
  "order": 1,
  "cards": [
    { "id": "s1-t001", "front": "Trabajo demasiado.", "back": "Ich arbeite zu viel." },
    { "id": "s1-t002", "front": "Tú también trabajas demasiado.", "back": "Du arbeitest auch zu viel." },
    { "id": "s1-t003", "front": "Él trabaja una barbaridad.", "back": "Er arbeitet viel zu viel." },
    { "id": "s1-t004", "front": "Fumo demasiado.", "back": "Ich rauche zu viel." },
    { "id": "s1-t005", "front": "Mi tío también fuma demasiado.", "back": "Mein Onkel raucht auch zu viel." },
    { "id": "s1-t006", "front": "Mi tía fuma una barbaridad.", "back": "Meine Tante raucht viel zu viel." },
    { "id": "s1-t007", "front": "Como demasiado.", "back": "Ich esse zu viel." },
    { "id": "s1-t008", "front": "Ella come demasiado chocolate.", "back": "Sie isst zu viel Schokolade." },
    { "id": "s1-t009", "front": "Él come una barbaridad de chocolate.", "back": "Er isst viel zu viel Schokolade." },
    { "id": "s1-t010", "front": "Tomo demasiado café.", "back": "Ich trinke zu viel Kaffee." },
    { "id": "s1-t011", "front": "Ellos beben demasiado vino.", "back": "Sie trinken zu viel Wein." },
    { "id": "s1-t012", "front": "Mi jefe bebe una barbaridad de cerveza.", "back": "Mein Chef trinkt viel zu viel Bier." },
    { "id": "s1-t013", "front": "Mi hermano sale demasiado.", "back": "Mein Bruder geht zu viel weg." },
    { "id": "s1-t014", "front": "Mi hermana también sale demasiado.", "back": "Meine Schwester geht auch zu viel weg." },
    { "id": "s1-t015", "front": "Mi prima sale una barbaridad.", "back": "Meine Cousine geht viel zu viel weg." },

    { "id": "s1-t016", "front": "Eso es lo suficientemente bueno.", "back": "Das ist gut genug." },
    { "id": "s1-t017", "front": "Eso no es lo suficientemente bueno.", "back": "Das ist nicht gut genug." },
    { "id": "s1-t018", "front": "No gano lo suficiente.", "back": "Ich verdiene nicht genug." },
    { "id": "s1-t019", "front": "Mi mujer no gana lo suficiente.", "back": "Meine Frau verdient nicht genug." },
    { "id": "s1-t020", "front": "Mi hijo tampoco gana lo suficiente.", "back": "Mein Sohn verdient auch nicht genug." },
    { "id": "s1-t021", "front": "No estudio lo suficiente.", "back": "Ich lerne nicht genug." },
    { "id": "s1-t022", "front": "Mi hija no estudia lo suficiente.", "back": "Meine Tochter lernt nicht genug." },
    { "id": "s1-t023", "front": "Mis hijos no estudian lo suficiente.", "back": "Meine Kinder lernen nicht genug." },
    { "id": "s1-t024", "front": "No como suficiente fruta.", "back": "Ich esse nicht genug Obst." },
    { "id": "s1-t025", "front": "El hijo de Ulrike no come suficiente verdura.", "back": "Ulrikes Sohn isst nicht genug Gemüse." },
    { "id": "s1-t026", "front": "La hija de Thomas tampoco come suficientes verduras.", "back": "Thomas' Tochter isst auch nicht genug Gemüse." },
    { "id": "s1-t027", "front": "No hago suficiente deporte.", "back": "Ich mache nicht genug Sport." },
    { "id": "s1-t028", "front": "Tú no haces suficiente deporte.", "back": "Du machst nicht genug Sport." },
    { "id": "s1-t029", "front": "Él tampoco hace suficiente deporte.", "back": "Er macht auch nicht genug Sport." },
    { "id": "s1-t030", "front": "Mi caballo no come lo suficiente. ¡Pobrecillo!", "back": "Mein Pferd frisst nicht genug. Das arme Ding!" },
    { "id": "s1-t031", "front": "Mi hámster no come lo suficiente. ¡Pobrecillo!", "back": "Mein Hamster frisst nicht genug. Das arme Ding!" },
    { "id": "s1-t032", "front": "Mi pájaro no come lo suficiente. ¡Pobrecillo!", "back": "Mein Vogel frisst nicht genug. Das arme Ding!" },

    { "id": "s1-t033", "front": "Hay demasiado tráfico en Madrid.", "back": "Es gibt zu viel Verkehr in Madrid." },
    { "id": "s1-t034", "front": "También hay demasiado tráfico en Barcelona.", "back": "Es gibt auch zu viel Verkehr in Barcelona." },
    { "id": "s1-t035", "front": "Hay demasiada delincuencia en São Paulo.", "back": "Es gibt zu viel Kriminalität in São Paulo." },
    { "id": "s1-t036", "front": "Hay demasiada pobreza en el mundo.", "back": "Es gibt zu viel Armut in der Welt." },
    { "id": "s1-t037", "front": "Hay demasiada delincuencia en la capital.", "back": "Es gibt zu viel Kriminalität in der Hauptstadt." },
    { "id": "s1-t038", "front": "Hay demasiado tráfico en el centro de la ciudad.", "back": "Es gibt zu viel Verkehr in der Innenstadt." },
    { "id": "s1-t039", "front": "Hay demasiado desempleo en el norte.", "back": "Es gibt zu viel Arbeitslosigkeit im Norden." },
    { "id": "s1-t040", "front": "Hay demasiada corrupción en el norte.", "back": "Es gibt zu viel Korruption im Norden." },
    { "id": "s1-t041", "front": "Hay demasiada pobreza en mi país.", "back": "Es gibt zu viel Armut in meinem Land." },
    { "id": "s1-t042", "front": "Hay demasiada delincuencia en mi barrio.", "back": "Es gibt zu viel Kriminalität in meinem Viertel." },
    { "id": "s1-t043", "front": "Hay demasiado ruido en mi calle.", "back": "Es gibt zu viel Lärm in meiner Straße." },
    { "id": "s1-t044", "front": "Hay demasiado desempleo en mi ciudad.", "back": "Es gibt zu viel Arbeitslosigkeit in meiner Stadt." },
    { "id": "s1-t045", "front": "Hay demasiada corrupción en mi ciudad.", "back": "Es gibt zu viel Korruption in meiner Stadt." },

    { "id": "s1-t046", "front": "Hay demasiada gente en el mundo.", "back": "Es gibt zu viele Menschen in der Welt." },
    { "id": "s1-t047", "front": "Hay demasiada gente en la tienda.", "back": "Da sind zu viele Leute im Laden." },
    { "id": "s1-t048", "front": "Hay demasiados delincuentes.", "back": "Es gibt zu viele Kriminelle." },
    { "id": "s1-t049", "front": "Hay demasiados parados.", "back": "Es gibt zu viele Arbeitslose." },
    { "id": "s1-t050", "front": "Hay demasiada gente pobre.", "back": "Es gibt zu viele arme Menschen." },
    { "id": "s1-t051", "front": "Hay demasiada gente en la panadería.", "back": "Da sind zu viele Leute in der Bäckerei." },
    { "id": "s1-t052", "front": "Hay demasiada gente pobre en el mundo.", "back": "Es gibt zu viele Arme in der Welt." },
    { "id": "s1-t053", "front": "Hay demasiados coches en la ciudad.", "back": "Es gibt zu viele Autos in der Stadt." },
    { "id": "s1-t054", "front": "Hay demasiados niños en el restaurante.", "back": "Da sind zu viele Kinder im Restaurant." },
    { "id": "s1-t055", "front": "Hay demasiados parados en el norte.", "back": "Es gibt zu viele Arbeitslose im Norden." },
    { "id": "s1-t056", "front": "Hay demasiados árboles en mi jardín.", "back": "Es gibt zu viele Bäume in meinem Garten." },
    { "id": "s1-t057", "front": "Hay demasiados tomates en mi ensalada.", "back": "Es gibt zu viele Tomaten in meinem Salat." },
    { "id": "s1-t058", "front": "Hay demasiados parados en mi país.", "back": "Es gibt zu viele Arbeitslose in meinem Land." },
    { "id": "s1-t059", "front": "Hay demasiados libros en mi casa.", "back": "Es gibt zu viele Bücher in meiner Wohnung." },
    { "id": "s1-t060", "front": "Hay demasiados libros en mi ciudad.", "back": "Es gibt zu viele Bücher in meiner Stadt." },
    { "id": "s1-t061", "front": "Hay demasiada gente en mi empresa.", "back": "Es gibt zu viele Leute in meiner Firma." },

    { "id": "s1-t062", "front": "No tengo suficiente tiempo.", "back": "Ich habe nicht genug Zeit." },
    { "id": "s1-t063", "front": "No tengo suficiente trabajo.", "back": "Ich habe nicht genug Arbeit." },
    { "id": "s1-t064", "front": "No tengo suficiente dinero.", "back": "Ich habe nicht genug Geld." },
    { "id": "s1-t065", "front": "No tenemos suficiente libertad.", "back": "Wir haben nicht genug Freiheit." },
    { "id": "s1-t066", "front": "No tenemos suficiente dinero.", "back": "Wir haben nicht genug Geld." },
    { "id": "s1-t067", "front": "No tenemos suficiente experiencia.", "back": "Wir haben nicht genug Erfahrung." },
    { "id": "s1-t068", "front": "¿Tienes suficiente azúcar? ¿Quieres más?", "back": "Hast du genug Zucker? Möchtest du mehr?" },
    { "id": "s1-t069", "front": "¿Tienes suficiente pimienta? ¿Quieres más?", "back": "Hast du genug Pfeffer? Möchtest du mehr?" },
    { "id": "s1-t070", "front": "¿Tienes suficiente sal? ¿Quieres más?", "back": "Hast du genug Salz? Möchtest du mehr?" },
    { "id": "s1-t071", "front": "¿Tenéis suficiente salsa? ¿Queréis más?", "back": "Habt ihr genug Soße? Möchtet ihr mehr?" },
    { "id": "s1-t072", "front": "¿Tenéis suficiente vino? ¿Queréis más?", "back": "Habt ihr genug Wein? Möchtet ihr mehr?" },
    { "id": "s1-t073", "front": "¿Tenéis suficiente agua? ¿Queréis más?", "back": "Habt ihr genug Wasser? Möchtet ihr mehr?" },
    { "id": "s1-t074", "front": "¿Tiene usted suficiente leche? ¿Quiere más?", "back": "Haben Sie genug Milch? Möchten Sie mehr?" },
    { "id": "s1-t075", "front": "¿Tiene usted suficiente aceite de oliva? ¿Quiere más?", "back": "Haben Sie genug Olivenöl? Möchten Sie mehr?" },
    { "id": "s1-t076", "front": "¿Tiene usted suficiente salsa? ¿Quiere más?", "back": "Haben Sie genug Soße? Möchten Sie mehr?" },

    { "id": "s1-t077", "front": "No tengo suficientes zapatos.", "back": "Ich habe nicht genug Schuhe." },
    { "id": "s1-t078", "front": "No tengo suficientes calcetines.", "back": "Ich habe nicht genug Socken." },
    { "id": "s1-t079", "front": "No tengo suficientes corbatas.", "back": "Ich habe nicht genug Krawatten." },
    { "id": "s1-t080", "front": "No tengo suficientes pantalones.", "back": "Ich habe nicht genug Hosen." },
    { "id": "s1-t081", "front": "No tengo suficientes calzoncillos.", "back": "Ich habe nicht genug Unterhosen." },
    { "id": "s1-t082", "front": "No tengo suficientes camisas.", "back": "Ich habe nicht genug Hemden." },
    { "id": "s1-t083", "front": "No tengo suficientes sombreros. Necesito más.", "back": "Ich habe nicht genug Hüte. Ich brauche mehr." },
    { "id": "s1-t084", "front": "No tengo suficientes camisas. Necesito más.", "back": "Ich habe nicht genug Hemden. Ich brauche mehr." },
    { "id": "s1-t085", "front": "No tengo suficiente ropa interior. Necesito más.", "back": "Ich habe nicht genug Unterwäsche. Ich brauche mehr." },
    { "id": "s1-t086", "front": "Tengo suficientes calzoncillos. No necesito más, gracias, mamá.", "back": "Ich habe genug Unterhosen. Ich brauche nicht mehr, danke, Mama." },
    { "id": "s1-t087", "front": "Tengo suficientes calcetines. No necesito más, gracias, mamá.", "back": "Ich habe genug Socken. Ich brauche nicht mehr, danke, Mama." },
    { "id": "s1-t088", "front": "Tengo suficientes camisas. No necesito más, gracias, mamá.", "back": "Ich habe genug Hemden. Ich brauche nicht mehr, danke, Mama." },
    { "id": "s1-t089", "front": "¿De verdad que tienes suficientes calzoncillos, hijo?", "back": "Hast du wirklich genug Unterhosen, mein Sohn?" },
    { "id": "s1-t090", "front": "¿De verdad que tienes suficientes calcetines, hijo?", "back": "Hast du wirklich genug Socken, mein Sohn?" },
    { "id": "s1-t091", "front": "¿De verdad que tienes suficientes zapatos, hijo?", "back": "Hast du wirklich genug Schuhe, mein Sohn?" },
    { "id": "s1-t092", "front": "Sí, mamá.", "back": "Ja, Mama." },

    { "id": "s1-t093", "front": "Una coca-cola, por favor.", "back": "Eine Cola, bitte." },
    { "id": "s1-t094", "front": "Encendido / Apagado (señal)", "back": "An / Aus" },
    { "id": "s1-t095", "front": "100", "back": "hundert" },
    { "id": "s1-t096", "front": "200", "back": "zweihundert" },
    { "id": "s1-t097", "front": "300", "back": "dreihundert" },
    { "id": "s1-t098", "front": "400", "back": "vierhundert" },
    { "id": "s1-t099", "front": "500", "back": "fünfhundert" },
    { "id": "s1-t100", "front": "600", "back": "sechshundert" },
    { "id": "s1-t101", "front": "700", "back": "siebenhundert" },
    { "id": "s1-t102", "front": "800", "back": "achthundert" },
    { "id": "s1-t103", "front": "900", "back": "neunhundert" },
    { "id": "s1-t104", "front": "1.000", "back": "tausend" },
    { "id": "s1-t105", "front": "Son las nueve menos diez.", "back": "Es ist zehn vor neun." },
    { "id": "s1-t106", "front": "Son las dos menos diez.", "back": "Es ist zehn vor zwei." },
    { "id": "s1-t107", "front": "Son las siete menos diez.", "back": "Es ist zehn vor sieben." },
    { "id": "s1-t108", "front": "Son las cinco menos diez.", "back": "Es ist zehn vor fünf." },
    { "id": "s1-t109", "front": "Son las seis menos diez.", "back": "Es ist zehn vor sechs." },
    { "id": "s1-t110", "front": "Son las doce menos diez.", "back": "Es ist zehn vor zwölf." },
    { "id": "s1-t111", "front": "calcetines (plural)", "back": "die Socken" },
    { "id": "s1-t112", "front": "calzoncillos (plural)", "back": "die Unterhosen" },
    { "id": "s1-t113", "front": "camisas (plural)", "back": "die Hemden" },
    { "id": "s1-t114", "front": "personas / gente (plural)", "back": "die Menschen" },
    { "id": "s1-t115", "front": "sandalias (plural)", "back": "die Sandalen" },
    { "id": "s1-t116", "front": "delincuentes (plural)", "back": "die Kriminellen" },

    { "id": "s1-g001", "front": "¿Cómo se dice 'demasiado' antes de un verbo o sustantivo incontable?", "back": "Zu viel. Ej.: 'Ich arbeite zu viel' (Trabajo demasiado), 'Ich trinke zu viel Kaffee' (Tomo demasiado café)." },
    { "id": "s1-g002", "front": "¿Y para enfatizar 'una barbaridad / muchísimo'?", "back": "Viel zu viel. Ej.: 'Er arbeitet viel zu viel' (Él trabaja una barbaridad)." },
    { "id": "s1-g003", "front": "¿Cómo se dice 'demasiados/as' con sustantivos en plural?", "back": "Zu viele. Ej.: 'Es gibt zu viele Menschen' (Hay demasiada gente)." },
    { "id": "s1-g004", "front": "¿Cómo se dice 'lo suficientemente' o 'suficiente' en alemán?", "back": "Genug. Se coloca DESPUÉS del adjetivo: 'gut genug' (lo suficientemente bueno). Con sustantivos, ANTES: 'genug Geld' (suficiente dinero)." },
    { "id": "s1-g005", "front": "¿Y 'no suficiente / no lo suficientemente'?", "back": "Nicht genug. Ej.: 'Ich verdiene nicht genug' (No gano lo suficiente), 'Das ist nicht gut genug' (No es lo suficientemente bueno)." },
    { "id": "s1-g006", "front": "¿Cómo se dice 'hay' en alemán para algo general (no específico)?", "back": "Es gibt + acusativo. Ej.: 'Es gibt zu viel Verkehr in Madrid' (Hay demasiado tráfico en Madrid)." },
    { "id": "s1-g007", "front": "¿Y para algo concreto y localizado en ese momento?", "back": "Da ist / Da sind + nominativo. Ej.: 'Da sind zu viele Leute im Laden' (Hay demasiada gente en la tienda)." },
    { "id": "s1-g008", "front": "Conjuga 'verdienen' (ganar dinero) en presente.", "back": "ich verdiene, du verdienst, er/sie/es verdient, wir verdienen, ihr verdient, sie/Sie verdienen." },
    { "id": "s1-g009", "front": "¿Cómo se conjuga 'fressen' (comer los animales) en 3ª persona singular?", "back": "Er/sie/es frisst. Se usa para animales, nunca para personas (que usan 'essen')." },
    { "id": "s1-g010", "front": "¿Cómo cambia 'in' + sustantivo masculino al expresar lugar (dativo)?", "back": "in dem → 'im'. Ej.: 'im Norden' (en el norte), 'im Restaurant' (en el restaurante), 'im Laden' (en la tienda)." },
    { "id": "s1-g011", "front": "¿Cómo se forma 'en mi país / barrio' (neutro, dativo)?", "back": "in meinem + sustantivo neutro. Ej.: 'in meinem Land' (en mi país), 'in meinem Viertel' (en mi barrio)." },
    { "id": "s1-g012", "front": "¿Cómo se forma 'en mi ciudad / calle' (femenino, dativo)?", "back": "in meiner + sustantivo femenino. Ej.: 'in meiner Stadt' (en mi ciudad), 'in meiner Straße' (en mi calle), 'in meiner Firma' (en mi empresa)." },
    { "id": "s1-g013", "front": "¿Cómo se dice 'una Coca-Cola, por favor'?", "back": "Eine Cola, bitte. — Es la frase clave del libro 11." },
    { "id": "s1-g014", "front": "¿Qué significan los letreros 'An' y 'Aus'?", "back": "An = encendido. Aus = apagado. Aparecen en interruptores y aparatos." },
    { "id": "s1-g015", "front": "Cuenta de 100 en 100 hasta 1.000.", "back": "hundert, zweihundert, dreihundert, vierhundert, fünfhundert, sechshundert, siebenhundert, achthundert, neunhundert, tausend." },
    { "id": "s1-g016", "front": "¿Cómo se dice 'Son las X menos diez'?", "back": "Es ist zehn vor + hora. Ej.: 'Es ist zehn vor neun' = Son las nueve menos diez." },
    { "id": "s1-g017", "front": "¿Qué ciudad se visita en el Buch 11 y por qué es conocida?", "back": "Hannover, capital de Baja Sajonia (Niedersachsen). Conocida por los Jardines de Herrenhausen y por la feria de informática CeBIT." },
    { "id": "s1-g018", "front": "¿Qué personaje alemán se asocia con Hannover en este libro?", "back": "Gerhard Schröder, ex canciller de Alemania." },
    { "id": "s1-g019", "front": "¿Cómo se pide 'más' de algo a alguien (tú / vosotros / usted)?", "back": "Möchtest du mehr? / Möchtet ihr mehr? / Möchten Sie mehr?" },
    { "id": "s1-g020", "front": "¿Cómo dirías 'no necesito más, gracias'?", "back": "Ich brauche nicht mehr, danke." },
    { "id": "s1-g021", "front": "¿Para qué se usa 'wirklich' y cómo se pronuncia?", "back": "Wirklich = 'de verdad / realmente'. Se pronuncia /vírklij/. Ej.: 'Hast du wirklich genug Schuhe?' (¿De verdad que tienes suficientes zapatos?)." },
    { "id": "s1-g022", "front": "Plurales irregulares clave del Buch 11.", "back": "Unterhose → Unterhosen, Socke → Socken, Hemd → Hemden, Mensch → Menschen, Sandale → Sandalen, Krimineller → Kriminellen." }
  ]
}
